<?xml version="1.0" encoding="utf-8" standalone="yes" ?>
<T3locallang>
	<meta type="array">
		<type>database</type>
		<description>Language labels for TCA belonging to extension 'ad_google_maps'</description>
	</meta>
	<data type="array">
		<languageKey index="default" type="array">
			<label index="tx_adgooglemaps_domain_model_layer.coordinatesProvider.addresses">Addresses</label>
			<label index="tx_adgooglemaps_domain_model_layer.coordinatesProvider.addressGroups">Address groups</label>
			<label index="tx_adgooglemaps_domain_model_layer.addresses">Addresses</label>
			<label index="tx_adgooglemaps_domain_model_layer.addressGroups">Address groups</label>
		</languageKey>
		<languageKey index="de" type="array">
			<label index="tx_adgooglemaps_domain_model_layer.coordinatesProvider.addresses">Adressen</label>
			<label index="tx_adgooglemaps_domain_model_layer.coordinatesProvider.addressGroups">Adressgruppen</label>
			<label index="tx_adgooglemaps_domain_model_layer.addresses">Adressen</label>
			<label index="tx_adgooglemaps_domain_model_layer.addressGroups">Adressgruppen</label>
		</languageKey>
	</data>
</T3locallang>